eng_m/__init__.py
eng_m/core/__init__.py
eng_m/core/api.py
eng_m/core/depreciable.py
eng_m/core/interest.py
eng_m/core/loan.py
eng_m/core/project.py
eng_m/core/series.py
eng_m/series/__init__.py
eng_m/series/_equal_payment.py
eng_m/series/_geometric_gradient.py
eng_m/series/_linear_gradient.py
eng_m/util/__init__.py
eng_m/util/exceptions.py
eng_m/util/maps.py
eng_m/util/types.py
eng_m-0.1.1.dist-info/WHEEL
eng_m-0.1.1.dist-info/METADATA
eng_m-0.1.1.dist-info/RECORD
