Metadata-Version: 2.1
Name: eng_m
Version: 0.1.1
Summary: Tools for the University of Alberta's ENG M 401 class.
Author-email: Sunny Nian <sunny@nian.ca>
Requires-Python: >=3.9
Requires-Dist: sympy >= 1.11.1
Requires-Dist: numpy >= 1.24.2
Requires-Dist: mypy >= 1.1.1 ; extra == "dev"
Requires-Dist: black >= 23.3.0 ; extra == "dev"
Requires-Dist: pytest-cov >= 4.0.0 ; extra == "dev"
Requires-Dist: flake8 >= 6.0.0 ; extra == "dev"
Project-URL: documentation, https://nian.ca/docs/eng_m
Project-URL: repository, https://github.com/Mcnuget5/eng-m-401
Provides-Extra: dev
